<?xml version="1.0" encoding="windows-1252"?>
<openerp>
    <data>
        <!-- PARK/PARTNER -->		
        <record model="ir.ui.view" id="view_park_membership_partner_inherited_form">
            <field name="name">park.membership.partner.form</field>
            <field name="model">res.partner</field>						
            <field name="type">form</field>						
            <field name="arch" type="xml">
                <form string="Member" version="7.0">
                	
                </form>
            </field>
        </record>
		
        <record model="ir.ui.view" id="view_park_membership_partner_inherited_tree">
            <field name="name">park.membership.partner.tree</field>
            <field name="model">res.partner</field>			
            <field name="type">tree</field>						
            <field name="arch" type="xml">
                <tree string="Member">
                    <field name="name"/>
                </tree>
            </field>
        </record>

                                            
        <!-- PARK/ACTION -->
        <!-- MEMBERSHIP -->
		<record model="ir.actions.act_window" id="action_park_membership">
            <field name="name">Membership</field>
            <field name="res_model">res.partner</field>
            <field name="view_mode">tree,form</field>
        </record>		
                                                                                                                                                                                                                                                                                                	
    </data>                
</openerp>